pydartz/__init__.py
pydartz/cli.py
pydartz/communication.py
pydartz/database.py
pydartz/finishes.py
pydartz/game.py
pydartz/player.py
pydartz/session.py
pydartz-2.5.0.data/data/data/chase_the_sun.wav
pydartz-2.5.0.dist-info/licenses/LICENSE.txt
pydartz-2.5.0.dist-info/METADATA
pydartz-2.5.0.dist-info/WHEEL
pydartz-2.5.0.dist-info/entry_points.txt
pydartz-2.5.0.dist-info/top_level.txt
pydartz-2.5.0.dist-info/RECORD
