Metadata-Version: 2.4
Name: pydartz
Version: 2.5.0
Summary: command line assistant and library for playing darts
Author-email: Philipp Metzner <beth.aleph@yahoo.de>
License: GPLv3
Project-URL: Bug Tracker, https://github.com/pylipp/pydartz/issues
Project-URL: Documentation, https://github.com/pylipp/pydartz
Project-URL: Homepage, https://github.com/pylipp/pydartz
Project-URL: Source Code, https://github.com/pylipp/pydartz
Keywords: commandline darts
Classifier: Development Status :: 3 - Alpha
Classifier: Environment :: Console
Classifier: Intended Audience :: End Users/Desktop
Classifier: Intended Audience :: Other Audience
Classifier: License :: OSI Approved :: GNU General Public License v3 (GPLv3)
Classifier: Operating System :: Unix
Classifier: Programming Language :: Python :: 3.10
Classifier: Programming Language :: Python :: 3.11
Classifier: Programming Language :: Python :: 3.12
Classifier: Programming Language :: Python :: 3.13
Classifier: Programming Language :: Python :: 3.14
Classifier: Topic :: Games/Entertainment
Classifier: Topic :: Software Development :: Libraries :: Python Modules
Requires-Python: >=3.10
License-File: LICENSE.txt
Provides-Extra: audio
Requires-Dist: simpleaudio==1.0.4; extra == "audio"
Provides-Extra: develop
Requires-Dist: black==25.9.0; extra == "develop"
Requires-Dist: coverage==7.10.7; extra == "develop"
Requires-Dist: flake8-pyproject==1.2.3; extra == "develop"
Requires-Dist: isort==6.0.1; extra == "develop"
Requires-Dist: pre-commit==4.3.0; extra == "develop"
Provides-Extra: packaging
Requires-Dist: build; extra == "packaging"
Dynamic: license-file
